tubthumper/__init__.py
tubthumper/_interfaces.py
tubthumper/_retry_factory.py
tubthumper/_types.py
tubthumper/_version.py
tubthumper/py.typed
tubthumper-0.3.0.dist-info/METADATA
tubthumper-0.3.0.dist-info/WHEEL
tubthumper-0.3.0.dist-info/licenses/LICENSE
tubthumper-0.3.0.dist-info/RECORD
