Metadata-Version: 2.3
Name: tubthumper
Version: 0.3.0
Summary: Python package of retry utilities named after the English anarcho-communist rock band Chumbawamba's 1997 hit Tubthumping
Project-URL: Documentation, https://tubthumper.mattefay.com
Project-URL: Changelog, https://tubthumper.mattefay.com/en/stable/changelog.html
Project-URL: Source, https://github.com/matteosox/tubthumper
Project-URL: Bug Report, https://github.com/matteosox/tubthumper/issues/new/choose
Project-URL: Feature Request, https://github.com/matteosox/tubthumper/issues/new/choose
Author-email: Matt Fay <matt.e.fay@gmail.com>
License: Apache License, Version 2.0
License-File: LICENSE
Keywords: exponential-backoff,jitter,retry
Classifier: Development Status :: 4 - Beta
Classifier: Intended Audience :: Developers
Classifier: License :: OSI Approved :: Apache Software License
Classifier: Natural Language :: English
Classifier: Operating System :: OS Independent
Classifier: Programming Language :: Python
Classifier: Programming Language :: Python :: 3
Classifier: Programming Language :: Python :: 3 :: Only
Classifier: Programming Language :: Python :: 3.9
Classifier: Programming Language :: Python :: 3.10
Classifier: Programming Language :: Python :: 3.11
Classifier: Programming Language :: Python :: 3.12
Classifier: Programming Language :: Python :: 3.13
Classifier: Programming Language :: Python :: Implementation :: CPython
Classifier: Topic :: Software Development
Classifier: Topic :: Software Development :: Libraries
Classifier: Topic :: Software Development :: Libraries :: Python Modules
Classifier: Typing :: Typed
Requires-Python: >=3.9
Requires-Dist: typing-extensions; python_version < '3.10'
